cacheable_iter/__init__.py
cacheable_iter/async_cached_iterable.py
cacheable_iter/cached_iterable.py
cacheable_iter/core.py
cacheable_iter/helpers.py
cacheable_iterators-0.1.1.dist-info/LICENSE
cacheable_iterators-0.1.1.dist-info/METADATA
cacheable_iterators-0.1.1.dist-info/WHEEL
cacheable_iterators-0.1.1.dist-info/top_level.txt
cacheable_iterators-0.1.1.dist-info/RECORD
